dynamatic/__init__.py
dynamatic/core.py
dynamatic/enums.py
dynamatic/exceptions.py
dynamatic/expressions.py
dynamatic/indexes.py
dynamatic/table_mixins.py
dynamatic-1.0.0b5.dist-info/LICENSE
dynamatic-1.0.0b5.dist-info/METADATA
dynamatic-1.0.0b5.dist-info/WHEEL
dynamatic-1.0.0b5.dist-info/top_level.txt
dynamatic-1.0.0b5.dist-info/RECORD
