Metadata-Version: 2.1
Name: dynamatic
Version: 1.0.0b5
Summary: A DynamoDB library based on boto3
Home-page: https://github.com/chrisbrantley/dynamatic
Author: Chris Brantley
License: UNKNOWN
Platform: UNKNOWN
Classifier: Programming Language :: Python :: 3
Classifier: License :: OSI Approved :: MIT License
Classifier: Operating System :: OS Independent
Requires-Python: >=3.6
Requires-Dist: boto3 (>=1.9)
